http_constants/__init__.py
http_constants/header.py
http_constants/method.py
http_constants/schema.py
http_constants/status.py
http_status_codes-1.0.3.dist-info/LICENSE
http_status_codes-1.0.3.dist-info/METADATA
http_status_codes-1.0.3.dist-info/WHEEL
http_status_codes-1.0.3.dist-info/top_level.txt
http_status_codes-1.0.3.dist-info/RECORD
