Metadata-Version: 2.1
Name: http-status-codes
Version: 1.0.3
Summary: The set of standard http constants
Home-page: https://github.com/alewkinr/http-constants
Author: Ramil Aleshkin
Author-email: alewkinr@gmail.com
License: MIT
Download-URL: https://github.com/alewkinr/http-constants/archive/v1.0.0.tar.gz
Platform: UNKNOWN
Classifier: License :: OSI Approved :: MIT License
Classifier: Programming Language :: Python
Classifier: Programming Language :: Python :: 3
Classifier: Programming Language :: Python :: 3.6
Classifier: Programming Language :: Python :: Implementation :: CPython
Classifier: Programming Language :: Python :: Implementation :: PyPy
Requires-Python: >=3.6.0
